{
  "resources": [
    {
      "asset_id": "246c02476bca07c2bd17826fabd9cf54",
      "public_id": "My Photos/Rori_disney_princess",
      "folder": "My Photos",
      "filename": "Rori_disney_princess",
      "display_name": "Rori_disney_princess",
      "format": "jpg",
      "version": 1635499384,
      "resource_type": "image",
      "type": "upload",
      "created_at": "2021-10-29T09:23:04+00:00",
      "uploaded_at": "2021-10-29T09:23:04+00:00",
      "bytes": 547907,
      "backup_bytes": 0,
      "width": 1440,
      "height": 2160,
      "aspect_ratio": 0.66667,
      "pixels": 3110400,
      "url": "http://res.cloudinary.com/milliegrey/image/upload/v1635499384/My%20Photos/Rori_disney_princess.jpg",
      "secure_url": "https://res.cloudinary.com/milliegrey/image/upload/v1635499384/My%20Photos/Rori_disney_princess.jpg",
      "status": "active",
      "access_mode": "public",
      "access_control": null,
      "etag": "457ab48bf40322e7bd20f39961f410a4",
      "created_by": {
        "access_key": "462313613892389",
        "custom_id": "gaga.binx@gmail.com",
        "external_id": "551bcab9372d004621842d78700916"
      },
      "uploaded_by": {
        "access_key": "462313613892389",
        "custom_id": "gaga.binx@gmail.com",
        "external_id": "551bcab9372d004621842d78700916"
      }
    },
    {
      "asset_id": "b06de46a0b7d4c721210044d5683df2d",
      "public_id": "My Photos/Fall_Rori-235-200925_a8emsp",
      "folder": "My Photos",
      "filename": "Fall_Rori-235-200925_a8emsp",
      "display_name": "Fall_Rori-235-200925_a8emsp",
      "format": "jpg",
      "version": 1635499384,
      "resource_type": "image",
      "type": "upload",
      "created_at": "2021-10-29T09:23:04+00:00",
      "uploaded_at": "2021-10-29T09:23:04+00:00",
      "bytes": 507054,
      "backup_bytes": 0,
      "width": 1440,
      "height": 2160,
      "aspect_ratio": 0.66667,
      "pixels": 3110400,
      "url": "http://res.cloudinary.com/milliegrey/image/upload/v1635499384/My%20Photos/Fall_Rori-235-200925_a8emsp.jpg",
      "secure_url": "https://res.cloudinary.com/milliegrey/image/upload/v1635499384/My%20Photos/Fall_Rori-235-200925_a8emsp.jpg",
      "status": "active",
      "access_mode": "public",
      "access_control": null,
      "etag": "1af7eaa48cff1c65a6dc5f8b05bdf54f",
      "created_by": {
        "access_key": "462313613892389",
        "custom_id": "gaga.binx@gmail.com",
        "external_id": "551bcab9372d004621842d78700916"
      },
      "uploaded_by": {
        "access_key": "462313613892389",
        "custom_id": "gaga.binx@gmail.com",
        "external_id": "551bcab9372d004621842d78700916"
      }
    },
    {
      "asset_id": "47c2c50b8029f766e25adf524430099b",
      "public_id": "My Photos/perseids-014-200813_vdwnvy",
      "folder": "My Photos",
      "filename": "perseids-014-200813_vdwnvy",
      "display_name": "perseids-014-200813_vdwnvy",
      "format": "jpg",
      "version": 1635499383,
      "resource_type": "image",
      "type": "upload",
      "created_at": "2021-10-29T09:23:03+00:00",
      "uploaded_at": "2021-10-29T09:23:03+00:00",
      "bytes": 371359,
      "backup_bytes": 0,
      "width": 2160,
      "height": 1440,
      "aspect_ratio": 1.5,
      "pixels": 3110400,
      "url": "http://res.cloudinary.com/milliegrey/image/upload/v1635499383/My%20Photos/perseids-014-200813_vdwnvy.jpg",
      "secure_url": "https://res.cloudinary.com/milliegrey/image/upload/v1635499383/My%20Photos/perseids-014-200813_vdwnvy.jpg",
      "status": "active",
      "access_mode": "public",
      "access_control": null,
      "etag": "d57c847a862227f12eedb5627c2a5cce",
      "created_by": {
        "access_key": "462313613892389",
        "custom_id": "gaga.binx@gmail.com",
        "external_id": "551bcab9372d004621842d78700916"
      },
      "uploaded_by": {
        "access_key": "462313613892389",
        "custom_id": "gaga.binx@gmail.com",
        "external_id": "551bcab9372d004621842d78700916"
      }
    },
    {
      "asset_id": "9645bc83dc4b5f5439d391341cb790be",
      "public_id": "My Photos/untitled_shoot-027-161010_mwofsr",
      "folder": "My Photos",
      "filename": "untitled_shoot-027-161010_mwofsr",
      "display_name": "untitled_shoot-027-161010_mwofsr",
      "format": "jpg",
      "version": 1635499383,
      "resource_type": "image",
      "type": "upload",
      "created_at": "2021-10-29T09:23:03+00:00",
      "uploaded_at": "2021-10-29T09:23:03+00:00",
      "bytes": 405685,
      "backup_bytes": 0,
      "width": 2160,
      "height": 1440,
      "aspect_ratio": 1.5,
      "pixels": 3110400,
      "url": "http://res.cloudinary.com/milliegrey/image/upload/v1635499383/My%20Photos/untitled_shoot-027-161010_mwofsr.jpg",
      "secure_url": "https://res.cloudinary.com/milliegrey/image/upload/v1635499383/My%20Photos/untitled_shoot-027-161010_mwofsr.jpg",
      "status": "active",
      "access_mode": "public",
      "access_control": null,
      "etag": "f3c0fbd9e8c4fe756f81fcb68ff6d4e5",
      "created_by": {
        "access_key": "462313613892389",
        "custom_id": "gaga.binx@gmail.com",
        "external_id": "551bcab9372d004621842d78700916"
      },
      "uploaded_by": {
        "access_key": "462313613892389",
        "custom_id": "gaga.binx@gmail.com",
        "external_id": "551bcab9372d004621842d78700916"
      }
    },
    {
      "asset_id": "82df18dc780021c33c957278ef06b9ff",
      "public_id": "My Photos/untitled_shoot-139-161010_j4nlex",
      "folder": "My Photos",
      "filename": "untitled_shoot-139-161010_j4nlex",
      "display_name": "untitled_shoot-139-161010_j4nlex",
      "format": "jpg",
      "version": 1635499383,
      "resource_type": "image",
      "type": "upload",
      "created_at": "2021-10-29T09:23:03+00:00",
      "uploaded_at": "2021-10-29T09:23:03+00:00",
      "bytes": 768853,
      "backup_bytes": 0,
      "width": 1440,
      "height": 2160,
      "aspect_ratio": 0.66667,
      "pixels": 3110400,
      "url": "http://res.cloudinary.com/milliegrey/image/upload/v1635499383/My%20Photos/untitled_shoot-139-161010_j4nlex.jpg",
      "secure_url": "https://res.cloudinary.com/milliegrey/image/upload/v1635499383/My%20Photos/untitled_shoot-139-161010_j4nlex.jpg",
      "status": "active",
      "access_mode": "public",
      "access_control": null,
      "etag": "256eff75b772b4ee780ae1ee2606628b",
      "created_by": {
        "access_key": "462313613892389",
        "custom_id": "gaga.binx@gmail.com",
        "external_id": "551bcab9372d004621842d78700916"
      },
      "uploaded_by": {
        "access_key": "462313613892389",
        "custom_id": "gaga.binx@gmail.com",
        "external_id": "551bcab9372d004621842d78700916"
      }
    },
    {
      "asset_id": "4385ff3983845b11c9159ee82c32fb4d",
      "public_id": "My Photos/untitled_shoot-044-180701_znyldn",
      "folder": "My Photos",
      "filename": "untitled_shoot-044-180701_znyldn",
      "display_name": "untitled_shoot-044-180701_znyldn",
      "format": "jpg",
      "version": 1635499383,
      "resource_type": "image",
      "type": "upload",
      "created_at": "2021-10-29T09:23:03+00:00",
      "uploaded_at": "2021-10-29T09:23:03+00:00",
      "bytes": 341196,
      "backup_bytes": 0,
      "width": 1628,
      "height": 1440,
      "aspect_ratio": 1.13056,
      "pixels": 2344320,
      "url": "http://res.cloudinary.com/milliegrey/image/upload/v1635499383/My%20Photos/untitled_shoot-044-180701_znyldn.jpg",
      "secure_url": "https://res.cloudinary.com/milliegrey/image/upload/v1635499383/My%20Photos/untitled_shoot-044-180701_znyldn.jpg",
      "status": "active",
      "access_mode": "public",
      "access_control": null,
      "etag": "c7b3686dc94b46be8c17e3c9113f1e5e",
      "created_by": {
        "access_key": "462313613892389",
        "custom_id": "gaga.binx@gmail.com",
        "external_id": "551bcab9372d004621842d78700916"
      },
      "uploaded_by": {
        "access_key": "462313613892389",
        "custom_id": "gaga.binx@gmail.com",
        "external_id": "551bcab9372d004621842d78700916"
      }
    },
    {
      "asset_id": "cf1b3565d976124395030ae6e05f1fad",
      "public_id": "My Photos/Mac_Tinder-074-200111_segego",
      "folder": "My Photos",
      "filename": "Mac_Tinder-074-200111_segego",
      "display_name": "Mac_Tinder-074-200111_segego",
      "format": "jpg",
      "version": 1635499383,
      "resource_type": "image",
      "type": "upload",
      "created_at": "2021-10-29T09:23:03+00:00",
      "uploaded_at": "2021-10-29T09:23:03+00:00",
      "bytes": 547749,
      "backup_bytes": 0,
      "width": 1440,
      "height": 2160,
      "aspect_ratio": 0.66667,
      "pixels": 3110400,
      "url": "http://res.cloudinary.com/milliegrey/image/upload/v1635499383/My%20Photos/Mac_Tinder-074-200111_segego.jpg",
      "secure_url": "https://res.cloudinary.com/milliegrey/image/upload/v1635499383/My%20Photos/Mac_Tinder-074-200111_segego.jpg",
      "status": "active",
      "access_mode": "public",
      "access_control": null,
      "etag": "b9431f0e4ceb4f9ebf78ab69279efaeb",
      "created_by": {
        "access_key": "462313613892389",
        "custom_id": "gaga.binx@gmail.com",
        "external_id": "551bcab9372d004621842d78700916"
      },
      "uploaded_by": {
        "access_key": "462313613892389",
        "custom_id": "gaga.binx@gmail.com",
        "external_id": "551bcab9372d004621842d78700916"
      }
    },
    {
      "asset_id": "53bae93829119cdfbfe951fe79dd0243",
      "public_id": "My Photos/Fall_Rori-297-200925_qdwfvi",
      "folder": "My Photos",
      "filename": "Fall_Rori-297-200925_qdwfvi",
      "display_name": "Fall_Rori-297-200925_qdwfvi",
      "format": "jpg",
      "version": 1635499383,
      "resource_type": "image",
      "type": "upload",
      "created_at": "2021-10-29T09:23:03+00:00",
      "uploaded_at": "2021-10-29T09:23:03+00:00",
      "bytes": 716305,
      "backup_bytes": 0,
      "width": 1440,
      "height": 2160,
      "aspect_ratio": 0.66667,
      "pixels": 3110400,
      "url": "http://res.cloudinary.com/milliegrey/image/upload/v1635499383/My%20Photos/Fall_Rori-297-200925_qdwfvi.jpg",
      "secure_url": "https://res.cloudinary.com/milliegrey/image/upload/v1635499383/My%20Photos/Fall_Rori-297-200925_qdwfvi.jpg",
      "status": "active",
      "access_mode": "public",
      "access_control": null,
      "etag": "419da7857b9f9ff1262c198e55a60eef",
      "created_by": {
        "access_key": "462313613892389",
        "custom_id": "gaga.binx@gmail.com",
        "external_id": "551bcab9372d004621842d78700916"
      },
      "uploaded_by": {
        "access_key": "462313613892389",
        "custom_id": "gaga.binx@gmail.com",
        "external_id": "551bcab9372d004621842d78700916"
      }
    },
    {
      "asset_id": "4fa0444c753a291477f3b5b6b7ae54e0",
      "public_id": "My Photos/OttawaTrip-043-160713_n7mvlb",
      "folder": "My Photos",
      "filename": "OttawaTrip-043-160713_n7mvlb",
      "display_name": "OttawaTrip-043-160713_n7mvlb",
      "format": "jpg",
      "version": 1635499201,
      "resource_type": "image",
      "type": "upload",
      "created_at": "2021-10-29T09:20:01+00:00",
      "uploaded_at": "2021-10-29T09:20:01+00:00",
      "bytes": 9956995,
      "backup_bytes": 0,
      "width": 6000,
      "height": 4000,
      "aspect_ratio": 1.5,
      "pixels": 24000000,
      "url": "http://res.cloudinary.com/milliegrey/image/upload/v1635499201/My%20Photos/OttawaTrip-043-160713_n7mvlb.jpg",
      "secure_url": "https://res.cloudinary.com/milliegrey/image/upload/v1635499201/My%20Photos/OttawaTrip-043-160713_n7mvlb.jpg",
      "status": "active",
      "access_mode": "public",
      "access_control": null,
      "etag": "d6e76d797609968297f628118a4de961",
      "created_by": {
        "access_key": "462313613892389",
        "custom_id": "gaga.binx@gmail.com",
        "external_id": "551bcab9372d004621842d78700916"
      },
      "uploaded_by": {
        "access_key": "462313613892389",
        "custom_id": "gaga.binx@gmail.com",
        "external_id": "551bcab9372d004621842d78700916"
      }
    },
    {
      "asset_id": "42aaf34386850286e0ef4eaed0cbdf84",
      "public_id": "My Photos/beach_things-018-170709_fglsds",
      "folder": "My Photos",
      "filename": "beach_things-018-170709_fglsds",
      "display_name": "beach_things-018-170709_fglsds",
      "format": "jpg",
      "version": 1635499201,
      "resource_type": "image",
      "type": "upload",
      "created_at": "2021-10-29T09:20:01+00:00",
      "uploaded_at": "2021-10-29T09:20:01+00:00",
      "bytes": 9680764,
      "backup_bytes": 0,
      "width": 4000,
      "height": 6000,
      "aspect_ratio": 0.66667,
      "pixels": 24000000,
      "url": "http://res.cloudinary.com/milliegrey/image/upload/v1635499201/My%20Photos/beach_things-018-170709_fglsds.jpg",
      "secure_url": "https://res.cloudinary.com/milliegrey/image/upload/v1635499201/My%20Photos/beach_things-018-170709_fglsds.jpg",
      "status": "active",
      "access_mode": "public",
      "access_control": null,
      "etag": "9c2e8bcb3bd058e63d52605e6786276b",
      "created_by": {
        "access_key": "462313613892389",
        "custom_id": "gaga.binx@gmail.com",
        "external_id": "551bcab9372d004621842d78700916"
      },
      "uploaded_by": {
        "access_key": "462313613892389",
        "custom_id": "gaga.binx@gmail.com",
        "external_id": "551bcab9372d004621842d78700916"
      }
    },
    {
      "asset_id": "a399e040694783a18c07a4c65f22a9b3",
      "public_id": "My Photos/beach_things-013-170709_kwphut",
      "folder": "My Photos",
      "filename": "beach_things-013-170709_kwphut",
      "display_name": "beach_things-013-170709_kwphut",
      "format": "jpg",
      "version": 1635499200,
      "resource_type": "image",
      "type": "upload",
      "created_at": "2021-10-29T09:20:00+00:00",
      "uploaded_at": "2021-10-29T09:20:00+00:00",
      "bytes": 9655546,
      "backup_bytes": 0,
      "width": 4000,
      "height": 6000,
      "aspect_ratio": 0.66667,
      "pixels": 24000000,
      "url": "http://res.cloudinary.com/milliegrey/image/upload/v1635499200/My%20Photos/beach_things-013-170709_kwphut.jpg",
      "secure_url": "https://res.cloudinary.com/milliegrey/image/upload/v1635499200/My%20Photos/beach_things-013-170709_kwphut.jpg",
      "status": "active",
      "access_mode": "public",
      "access_control": null,
      "etag": "8433b7daf1384039dad45fac20ac4f02",
      "created_by": {
        "access_key": "462313613892389",
        "custom_id": "gaga.binx@gmail.com",
        "external_id": "551bcab9372d004621842d78700916"
      },
      "uploaded_by": {
        "access_key": "462313613892389",
        "custom_id": "gaga.binx@gmail.com",
        "external_id": "551bcab9372d004621842d78700916"
      }
    },
    {
      "asset_id": "8bed83911e9e69b86ed19bb23d4bdae9",
      "public_id": "My Photos/auroras_in_the_backyard-022-170907_whisdz",
      "folder": "My Photos",
      "filename": "auroras_in_the_backyard-022-170907_whisdz",
      "display_name": "auroras_in_the_backyard-022-170907_whisdz",
      "format": "jpg",
      "version": 1635499200,
      "resource_type": "image",
      "type": "upload",
      "created_at": "2021-10-29T09:20:00+00:00",
      "uploaded_at": "2021-10-29T09:20:00+00:00",
      "bytes": 8707147,
      "backup_bytes": 0,
      "width": 6000,
      "height": 4000,
      "aspect_ratio": 1.5,
      "pixels": 24000000,
      "url": "http://res.cloudinary.com/milliegrey/image/upload/v1635499200/My%20Photos/auroras_in_the_backyard-022-170907_whisdz.jpg",
      "secure_url": "https://res.cloudinary.com/milliegrey/image/upload/v1635499200/My%20Photos/auroras_in_the_backyard-022-170907_whisdz.jpg",
      "status": "active",
      "access_mode": "public",
      "access_control": null,
      "etag": "1b5ba08e8dc8603d78ef4fb95f9d3611",
      "created_by": {
        "access_key": "462313613892389",
        "custom_id": "gaga.binx@gmail.com",
        "external_id": "551bcab9372d004621842d78700916"
      },
      "uploaded_by": {
        "access_key": "462313613892389",
        "custom_id": "gaga.binx@gmail.com",
        "external_id": "551bcab9372d004621842d78700916"
      }
    },
    {
      "asset_id": "56a7a467a54e12e3fb65c692a050334b",
      "public_id": "My Photos/annaautumn2017-168-171015_fbbwlk",
      "folder": "My Photos",
      "filename": "annaautumn2017-168-171015_fbbwlk",
      "display_name": "annaautumn2017-168-171015_fbbwlk",
      "format": "jpg",
      "version": 1635499199,
      "resource_type": "image",
      "type": "upload",
      "created_at": "2021-10-29T09:19:59+00:00",
      "uploaded_at": "2021-10-29T09:19:59+00:00",
      "bytes": 9309742,
      "backup_bytes": 0,
      "width": 4000,
      "height": 6000,
      "aspect_ratio": 0.66667,
      "pixels": 24000000,
      "url": "http://res.cloudinary.com/milliegrey/image/upload/v1635499199/My%20Photos/annaautumn2017-168-171015_fbbwlk.jpg",
      "secure_url": "https://res.cloudinary.com/milliegrey/image/upload/v1635499199/My%20Photos/annaautumn2017-168-171015_fbbwlk.jpg",
      "status": "active",
      "access_mode": "public",
      "access_control": null,
      "etag": "0bd018ac2c59c9d7a8409c1bb25cb2e0",
      "created_by": {
        "access_key": "462313613892389",
        "custom_id": "gaga.binx@gmail.com",
        "external_id": "551bcab9372d004621842d78700916"
      },
      "uploaded_by": {
        "access_key": "462313613892389",
        "custom_id": "gaga.binx@gmail.com",
        "external_id": "551bcab9372d004621842d78700916"
      }
    },
    {
      "asset_id": "2fc710d927fe0914c59ee585bd468527",
      "public_id": "My Photos/x-t1-practice-003-180202_k1zuzp",
      "folder": "My Photos",
      "filename": "x-t1-practice-003-180202_k1zuzp",
      "display_name": "x-t1-practice-003-180202_k1zuzp",
      "format": "jpg",
      "version": 1635499199,
      "resource_type": "image",
      "type": "upload",
      "created_at": "2021-10-29T09:19:59+00:00",
      "uploaded_at": "2021-10-29T09:19:59+00:00",
      "bytes": 6348004,
      "backup_bytes": 0,
      "width": 3264,
      "height": 4896,
      "aspect_ratio": 0.66667,
      "pixels": 15980544,
      "url": "http://res.cloudinary.com/milliegrey/image/upload/v1635499199/My%20Photos/x-t1-practice-003-180202_k1zuzp.jpg",
      "secure_url": "https://res.cloudinary.com/milliegrey/image/upload/v1635499199/My%20Photos/x-t1-practice-003-180202_k1zuzp.jpg",
      "status": "active",
      "access_mode": "public",
      "access_control": null,
      "etag": "3330c5f1d510aad1e6c292bac3ffe8a8",
      "created_by": {
        "access_key": "462313613892389",
        "custom_id": "gaga.binx@gmail.com",
        "external_id": "551bcab9372d004621842d78700916"
      },
      "uploaded_by": {
        "access_key": "462313613892389",
        "custom_id": "gaga.binx@gmail.com",
        "external_id": "551bcab9372d004621842d78700916"
      }
    },
    {
      "asset_id": "0725dd0c8ff9d7aa547db1a550a60a12",
      "public_id": "My Photos/Headshots-304-170826_gpr4d9",
      "folder": "My Photos",
      "filename": "Headshots-304-170826_gpr4d9",
      "display_name": "Headshots-304-170826_gpr4d9",
      "format": "jpg",
      "version": 1635499198,
      "resource_type": "image",
      "type": "upload",
      "created_at": "2021-10-29T09:19:58+00:00",
      "uploaded_at": "2021-10-29T09:19:58+00:00",
      "bytes": 9628068,
      "backup_bytes": 0,
      "width": 4000,
      "height": 6000,
      "aspect_ratio": 0.66667,
      "pixels": 24000000,
      "url": "http://res.cloudinary.com/milliegrey/image/upload/v1635499198/My%20Photos/Headshots-304-170826_gpr4d9.jpg",
      "secure_url": "https://res.cloudinary.com/milliegrey/image/upload/v1635499198/My%20Photos/Headshots-304-170826_gpr4d9.jpg",
      "status": "active",
      "access_mode": "public",
      "access_control": null,
      "etag": "269a1a3b54013ba658bad70e535e4a46",
      "created_by": {
        "access_key": "462313613892389",
        "custom_id": "gaga.binx@gmail.com",
        "external_id": "551bcab9372d004621842d78700916"
      },
      "uploaded_by": {
        "access_key": "462313613892389",
        "custom_id": "gaga.binx@gmail.com",
        "external_id": "551bcab9372d004621842d78700916"
      }
    },
    {
      "asset_id": "f9aedb54f0b732b53a19f635e71c4a96",
      "public_id": "My Photos/Puddles-002-160801_b79g0x",
      "folder": "My Photos",
      "filename": "Puddles-002-160801_b79g0x",
      "display_name": "Puddles-002-160801_b79g0x",
      "format": "jpg",
      "version": 1635499197,
      "resource_type": "image",
      "type": "upload",
      "created_at": "2021-10-29T09:19:57+00:00",
      "uploaded_at": "2021-10-29T09:19:57+00:00",
      "bytes": 4769721,
      "backup_bytes": 0,
      "width": 6000,
      "height": 4000,
      "aspect_ratio": 1.5,
      "pixels": 24000000,
      "url": "http://res.cloudinary.com/milliegrey/image/upload/v1635499197/My%20Photos/Puddles-002-160801_b79g0x.jpg",
      "secure_url": "https://res.cloudinary.com/milliegrey/image/upload/v1635499197/My%20Photos/Puddles-002-160801_b79g0x.jpg",
      "status": "active",
      "access_mode": "public",
      "access_control": null,
      "etag": "e02614e51b048104d1a432f7be374a13",
      "created_by": {
        "access_key": "462313613892389",
        "custom_id": "gaga.binx@gmail.com",
        "external_id": "551bcab9372d004621842d78700916"
      },
      "uploaded_by": {
        "access_key": "462313613892389",
        "custom_id": "gaga.binx@gmail.com",
        "external_id": "551bcab9372d004621842d78700916"
      }
    },
    {
      "asset_id": "52d8621cf76cd729524b3be9526d62d9",
      "public_id": "My Photos/Foggy_Night-015-161127_j85tat",
      "folder": "My Photos",
      "filename": "Foggy_Night-015-161127_j85tat",
      "display_name": "Foggy_Night-015-161127_j85tat",
      "format": "jpg",
      "version": 1635499197,
      "resource_type": "image",
      "type": "upload",
      "created_at": "2021-10-29T09:19:57+00:00",
      "uploaded_at": "2021-10-29T09:19:57+00:00",
      "bytes": 8160782,
      "backup_bytes": 0,
      "width": 6000,
      "height": 4000,
      "aspect_ratio": 1.5,
      "pixels": 24000000,
      "url": "http://res.cloudinary.com/milliegrey/image/upload/v1635499197/My%20Photos/Foggy_Night-015-161127_j85tat.jpg",
      "secure_url": "https://res.cloudinary.com/milliegrey/image/upload/v1635499197/My%20Photos/Foggy_Night-015-161127_j85tat.jpg",
      "status": "active",
      "access_mode": "public",
      "access_control": null,
      "etag": "ebf619efc640ac884a0be8e215d5d663",
      "created_by": {
        "access_key": "462313613892389",
        "custom_id": "gaga.binx@gmail.com",
        "external_id": "551bcab9372d004621842d78700916"
      },
      "uploaded_by": {
        "access_key": "462313613892389",
        "custom_id": "gaga.binx@gmail.com",
        "external_id": "551bcab9372d004621842d78700916"
      }
    },
    {
      "asset_id": "0987bd51af2f661dc628f624600e9023",
      "public_id": "My Photos/Puddles-001-160801_lzfuog",
      "folder": "My Photos",
      "filename": "Puddles-001-160801_lzfuog",
      "display_name": "Puddles-001-160801_lzfuog",
      "format": "jpg",
      "version": 1635499196,
      "resource_type": "image",
      "type": "upload",
      "created_at": "2021-10-29T09:19:56+00:00",
      "uploaded_at": "2021-10-29T09:19:56+00:00",
      "bytes": 5842608,
      "backup_bytes": 0,
      "width": 6000,
      "height": 4000,
      "aspect_ratio": 1.5,
      "pixels": 24000000,
      "url": "http://res.cloudinary.com/milliegrey/image/upload/v1635499196/My%20Photos/Puddles-001-160801_lzfuog.jpg",
      "secure_url": "https://res.cloudinary.com/milliegrey/image/upload/v1635499196/My%20Photos/Puddles-001-160801_lzfuog.jpg",
      "status": "active",
      "access_mode": "public",
      "access_control": null,
      "etag": "b0d6f598742736b17a8177738070ab33",
      "created_by": {
        "access_key": "462313613892389",
        "custom_id": "gaga.binx@gmail.com",
        "external_id": "551bcab9372d004621842d78700916"
      },
      "uploaded_by": {
        "access_key": "462313613892389",
        "custom_id": "gaga.binx@gmail.com",
        "external_id": "551bcab9372d004621842d78700916"
      }
    },
    {
      "asset_id": "23136c2df7cff150059ab002506cdf9b",
      "public_id": "My Photos/MakeupAnnaGoodstuff-375-170727_vsvcwj",
      "folder": "My Photos",
      "filename": "MakeupAnnaGoodstuff-375-170727_vsvcwj",
      "display_name": "MakeupAnnaGoodstuff-375-170727_vsvcwj",
      "format": "jpg",
      "version": 1635499195,
      "resource_type": "image",
      "type": "upload",
      "created_at": "2021-10-29T09:19:55+00:00",
      "uploaded_at": "2021-10-29T09:19:55+00:00",
      "bytes": 4444526,
      "backup_bytes": 0,
      "width": 6000,
      "height": 4000,
      "aspect_ratio": 1.5,
      "pixels": 24000000,
      "url": "http://res.cloudinary.com/milliegrey/image/upload/v1635499195/My%20Photos/MakeupAnnaGoodstuff-375-170727_vsvcwj.jpg",
      "secure_url": "https://res.cloudinary.com/milliegrey/image/upload/v1635499195/My%20Photos/MakeupAnnaGoodstuff-375-170727_vsvcwj.jpg",
      "status": "active",
      "access_mode": "public",
      "access_control": null,
      "etag": "594352890a12c3c57e15541458e95d15",
      "created_by": {
        "access_key": "462313613892389",
        "custom_id": "gaga.binx@gmail.com",
        "external_id": "551bcab9372d004621842d78700916"
      },
      "uploaded_by": {
        "access_key": "462313613892389",
        "custom_id": "gaga.binx@gmail.com",
        "external_id": "551bcab9372d004621842d78700916"
      }
    },
    {
      "asset_id": "512ccace80569059a4cd36b720961a7b",
      "public_id": "My Photos/winterfest-019-180224-Edit_ofx5bq",
      "folder": "My Photos",
      "filename": "winterfest-019-180224-Edit_ofx5bq",
      "display_name": "winterfest-019-180224-Edit_ofx5bq",
      "format": "jpg",
      "version": 1635499195,
      "resource_type": "image",
      "type": "upload",
      "created_at": "2021-10-29T09:19:55+00:00",
      "uploaded_at": "2021-10-29T09:19:55+00:00",
      "bytes": 4261944,
      "backup_bytes": 0,
      "width": 3264,
      "height": 4896,
      "aspect_ratio": 0.66667,
      "pixels": 15980544,
      "url": "http://res.cloudinary.com/milliegrey/image/upload/v1635499195/My%20Photos/winterfest-019-180224-Edit_ofx5bq.jpg",
      "secure_url": "https://res.cloudinary.com/milliegrey/image/upload/v1635499195/My%20Photos/winterfest-019-180224-Edit_ofx5bq.jpg",
      "status": "active",
      "access_mode": "public",
      "access_control": null,
      "etag": "9e91cb3d58763a192dd3ef36c5bbc89c",
      "created_by": {
        "access_key": "462313613892389",
        "custom_id": "gaga.binx@gmail.com",
        "external_id": "551bcab9372d004621842d78700916"
      },
      "uploaded_by": {
        "access_key": "462313613892389",
        "custom_id": "gaga.binx@gmail.com",
        "external_id": "551bcab9372d004621842d78700916"
      }
    },
    {
      "asset_id": "5b8481b155ce2f90cdc491c2c699e2d3",
      "public_id": "My Photos/Headshots-292-170826_ta8oqt",
      "folder": "My Photos",
      "filename": "Headshots-292-170826_ta8oqt",
      "display_name": "Headshots-292-170826_ta8oqt",
      "format": "jpg",
      "version": 1635499195,
      "resource_type": "image",
      "type": "upload",
      "created_at": "2021-10-29T09:19:55+00:00",
      "uploaded_at": "2021-10-29T09:19:55+00:00",
      "bytes": 7282722,
      "backup_bytes": 0,
      "width": 3788,
      "height": 5682,
      "aspect_ratio": 0.66667,
      "pixels": 21523416,
      "url": "http://res.cloudinary.com/milliegrey/image/upload/v1635499195/My%20Photos/Headshots-292-170826_ta8oqt.jpg",
      "secure_url": "https://res.cloudinary.com/milliegrey/image/upload/v1635499195/My%20Photos/Headshots-292-170826_ta8oqt.jpg",
      "status": "active",
      "access_mode": "public",
      "access_control": null,
      "etag": "729b5d858b82144e9dfef8ffdb642b81",
      "created_by": {
        "access_key": "462313613892389",
        "custom_id": "gaga.binx@gmail.com",
        "external_id": "551bcab9372d004621842d78700916"
      },
      "uploaded_by": {
        "access_key": "462313613892389",
        "custom_id": "gaga.binx@gmail.com",
        "external_id": "551bcab9372d004621842d78700916"
      }
    },
    {
      "asset_id": "646874d428879f28275b69e3513896c2",
      "public_id": "My Photos/ryes_23rd-023-180421_lirrws",
      "folder": "My Photos",
      "filename": "ryes_23rd-023-180421_lirrws",
      "display_name": "ryes_23rd-023-180421_lirrws",
      "format": "jpg",
      "version": 1635499193,
      "resource_type": "image",
      "type": "upload",
      "created_at": "2021-10-29T09:19:53+00:00",
      "uploaded_at": "2021-10-29T09:19:53+00:00",
      "bytes": 3685728,
      "backup_bytes": 0,
      "width": 2176,
      "height": 3264,
      "aspect_ratio": 0.66667,
      "pixels": 7102464,
      "url": "http://res.cloudinary.com/milliegrey/image/upload/v1635499193/My%20Photos/ryes_23rd-023-180421_lirrws.jpg",
      "secure_url": "https://res.cloudinary.com/milliegrey/image/upload/v1635499193/My%20Photos/ryes_23rd-023-180421_lirrws.jpg",
      "status": "active",
      "access_mode": "public",
      "access_control": null,
      "etag": "a39d88a3caa95f7a8a87f6afe61a98bc",
      "created_by": {
        "access_key": "462313613892389",
        "custom_id": "gaga.binx@gmail.com",
        "external_id": "551bcab9372d004621842d78700916"
      },
      "uploaded_by": {
        "access_key": "462313613892389",
        "custom_id": "gaga.binx@gmail.com",
        "external_id": "551bcab9372d004621842d78700916"
      }
    },
    {
      "asset_id": "e899fada43c679ce451266099b1e01da",
      "public_id": "My Photos/winterfest-068-180224_ndrxi1",
      "folder": "My Photos",
      "filename": "winterfest-068-180224_ndrxi1",
      "display_name": "winterfest-068-180224_ndrxi1",
      "format": "jpg",
      "version": 1635499193,
      "resource_type": "image",
      "type": "upload",
      "created_at": "2021-10-29T09:19:53+00:00",
      "uploaded_at": "2021-10-29T09:19:53+00:00",
      "bytes": 2563956,
      "backup_bytes": 0,
      "width": 3443,
      "height": 2295,
      "aspect_ratio": 1.50022,
      "pixels": 7901685,
      "url": "http://res.cloudinary.com/milliegrey/image/upload/v1635499193/My%20Photos/winterfest-068-180224_ndrxi1.jpg",
      "secure_url": "https://res.cloudinary.com/milliegrey/image/upload/v1635499193/My%20Photos/winterfest-068-180224_ndrxi1.jpg",
      "status": "active",
      "access_mode": "public",
      "access_control": null,
      "etag": "6ecc9c9d0e21e0b67dc4e1fed7542fb3",
      "created_by": {
        "access_key": "462313613892389",
        "custom_id": "gaga.binx@gmail.com",
        "external_id": "551bcab9372d004621842d78700916"
      },
      "uploaded_by": {
        "access_key": "462313613892389",
        "custom_id": "gaga.binx@gmail.com",
        "external_id": "551bcab9372d004621842d78700916"
      }
    },
    {
      "asset_id": "f921f87f3e6e54bac373297e77f5f477",
      "public_id": "My Photos/untitled_shoot-233-190121_cropped_and_stuff_ixnmiq",
      "folder": "My Photos",
      "filename": "untitled_shoot-233-190121_cropped_and_stuff_ixnmiq",
      "display_name": "untitled_shoot-233-190121_cropped_and_stuff_ixnmiq",
      "format": "png",
      "version": 1635499192,
      "resource_type": "image",
      "type": "upload",
      "created_at": "2021-10-29T09:19:52+00:00",
      "uploaded_at": "2021-10-29T09:19:52+00:00",
      "bytes": 4784191,
      "backup_bytes": 0,
      "width": 5513,
      "height": 2075,
      "aspect_ratio": 2.65687,
      "pixels": 11439475,
      "url": "http://res.cloudinary.com/milliegrey/image/upload/v1635499192/My%20Photos/untitled_shoot-233-190121_cropped_and_stuff_ixnmiq.png",
      "secure_url": "https://res.cloudinary.com/milliegrey/image/upload/v1635499192/My%20Photos/untitled_shoot-233-190121_cropped_and_stuff_ixnmiq.png",
      "status": "active",
      "access_mode": "public",
      "access_control": null,
      "etag": "3a5d07f5893ed7b1d9028fd28b385748",
      "created_by": {
        "access_key": "462313613892389",
        "custom_id": "gaga.binx@gmail.com",
        "external_id": "551bcab9372d004621842d78700916"
      },
      "uploaded_by": {
        "access_key": "462313613892389",
        "custom_id": "gaga.binx@gmail.com",
        "external_id": "551bcab9372d004621842d78700916"
      }
    },
    {
      "asset_id": "27f11a80d257d44e4ced271b1a0006e7",
      "public_id": "My Photos/Fall_Rori-078-200925_isxaff",
      "folder": "My Photos",
      "filename": "Fall_Rori-078-200925_isxaff",
      "display_name": "Fall_Rori-078-200925_isxaff",
      "format": "jpg",
      "version": 1635499192,
      "resource_type": "image",
      "type": "upload",
      "created_at": "2021-10-29T09:19:52+00:00",
      "uploaded_at": "2021-10-29T09:19:52+00:00",
      "bytes": 10436938,
      "backup_bytes": 0,
      "width": 4000,
      "height": 6000,
      "aspect_ratio": 0.66667,
      "pixels": 24000000,
      "url": "http://res.cloudinary.com/milliegrey/image/upload/v1635499192/My%20Photos/Fall_Rori-078-200925_isxaff.jpg",
      "secure_url": "https://res.cloudinary.com/milliegrey/image/upload/v1635499192/My%20Photos/Fall_Rori-078-200925_isxaff.jpg",
      "status": "active",
      "access_mode": "public",
      "access_control": null,
      "etag": "349f742f93adf26d93f1d2a6c32f5a69",
      "created_by": {
        "access_key": "462313613892389",
        "custom_id": "gaga.binx@gmail.com",
        "external_id": "551bcab9372d004621842d78700916"
      },
      "uploaded_by": {
        "access_key": "462313613892389",
        "custom_id": "gaga.binx@gmail.com",
        "external_id": "551bcab9372d004621842d78700916"
      }
    },
    {
      "asset_id": "9d5f52b85c453aea8ea3575441e93906",
      "public_id": "My Photos/Headshots-324-170826-Edit_stc6tc",
      "folder": "My Photos",
      "filename": "Headshots-324-170826-Edit_stc6tc",
      "display_name": "Headshots-324-170826-Edit_stc6tc",
      "format": "jpg",
      "version": 1635499192,
      "resource_type": "image",
      "type": "upload",
      "created_at": "2021-10-29T09:19:52+00:00",
      "uploaded_at": "2021-10-29T09:19:52+00:00",
      "bytes": 4902647,
      "backup_bytes": 0,
      "width": 4000,
      "height": 4058,
      "aspect_ratio": 0.98571,
      "pixels": 16232000,
      "url": "http://res.cloudinary.com/milliegrey/image/upload/v1635499192/My%20Photos/Headshots-324-170826-Edit_stc6tc.jpg",
      "secure_url": "https://res.cloudinary.com/milliegrey/image/upload/v1635499192/My%20Photos/Headshots-324-170826-Edit_stc6tc.jpg",
      "status": "active",
      "access_mode": "public",
      "access_control": null,
      "etag": "f5823cae287214328c64a377605b9904",
      "created_by": {
        "access_key": "462313613892389",
        "custom_id": "gaga.binx@gmail.com",
        "external_id": "551bcab9372d004621842d78700916"
      },
      "uploaded_by": {
        "access_key": "462313613892389",
        "custom_id": "gaga.binx@gmail.com",
        "external_id": "551bcab9372d004621842d78700916"
      }
    },
    {
      "asset_id": "c599bf610af1d27d9f3f10bcbae2378b",
      "public_id": "My Photos/ryes_23rd-024-180421_mnegl4",
      "folder": "My Photos",
      "filename": "ryes_23rd-024-180421_mnegl4",
      "display_name": "ryes_23rd-024-180421_mnegl4",
      "format": "jpg",
      "version": 1635499192,
      "resource_type": "image",
      "type": "upload",
      "created_at": "2021-10-29T09:19:52+00:00",
      "uploaded_at": "2021-10-29T09:19:52+00:00",
      "bytes": 3352201,
      "backup_bytes": 0,
      "width": 2176,
      "height": 3264,
      "aspect_ratio": 0.66667,
      "pixels": 7102464,
      "url": "http://res.cloudinary.com/milliegrey/image/upload/v1635499192/My%20Photos/ryes_23rd-024-180421_mnegl4.jpg",
      "secure_url": "https://res.cloudinary.com/milliegrey/image/upload/v1635499192/My%20Photos/ryes_23rd-024-180421_mnegl4.jpg",
      "status": "active",
      "access_mode": "public",
      "access_control": null,
      "etag": "15a73752ed099416a7242dbadf57572f",
      "created_by": {
        "access_key": "462313613892389",
        "custom_id": "gaga.binx@gmail.com",
        "external_id": "551bcab9372d004621842d78700916"
      },
      "uploaded_by": {
        "access_key": "462313613892389",
        "custom_id": "gaga.binx@gmail.com",
        "external_id": "551bcab9372d004621842d78700916"
      }
    },
    {
      "asset_id": "36596f8941a6cf9481a3f8e73526d898",
      "public_id": "My Photos/x-t1-practice-016-180207_ugd7xy",
      "folder": "My Photos",
      "filename": "x-t1-practice-016-180207_ugd7xy",
      "display_name": "x-t1-practice-016-180207_ugd7xy",
      "format": "jpg",
      "version": 1635499192,
      "resource_type": "image",
      "type": "upload",
      "created_at": "2021-10-29T09:19:52+00:00",
      "uploaded_at": "2021-10-29T09:19:52+00:00",
      "bytes": 4449177,
      "backup_bytes": 0,
      "width": 3264,
      "height": 4896,
      "aspect_ratio": 0.66667,
      "pixels": 15980544,
      "url": "http://res.cloudinary.com/milliegrey/image/upload/v1635499192/My%20Photos/x-t1-practice-016-180207_ugd7xy.jpg",
      "secure_url": "https://res.cloudinary.com/milliegrey/image/upload/v1635499192/My%20Photos/x-t1-practice-016-180207_ugd7xy.jpg",
      "status": "active",
      "access_mode": "public",
      "access_control": null,
      "etag": "7ac1141065fc9a4c97fd79c03aa60cdc",
      "created_by": {
        "access_key": "462313613892389",
        "custom_id": "gaga.binx@gmail.com",
        "external_id": "551bcab9372d004621842d78700916"
      },
      "uploaded_by": {
        "access_key": "462313613892389",
        "custom_id": "gaga.binx@gmail.com",
        "external_id": "551bcab9372d004621842d78700916"
      }
    },
    {
      "asset_id": "85fa127cd20270f90658a7fc89bc7d07",
      "public_id": "My Photos/duck_pond_2018-073-181007_irbx4q",
      "folder": "My Photos",
      "filename": "duck_pond_2018-073-181007_irbx4q",
      "display_name": "duck_pond_2018-073-181007_irbx4q",
      "format": "jpg",
      "version": 1635499192,
      "resource_type": "image",
      "type": "upload",
      "created_at": "2021-10-29T09:19:52+00:00",
      "uploaded_at": "2021-10-29T09:19:52+00:00",
      "bytes": 3174750,
      "backup_bytes": 0,
      "width": 2500,
      "height": 1658,
      "aspect_ratio": 1.50784,
      "pixels": 4145000,
      "url": "http://res.cloudinary.com/milliegrey/image/upload/v1635499192/My%20Photos/duck_pond_2018-073-181007_irbx4q.jpg",
      "secure_url": "https://res.cloudinary.com/milliegrey/image/upload/v1635499192/My%20Photos/duck_pond_2018-073-181007_irbx4q.jpg",
      "status": "active",
      "access_mode": "public",
      "access_control": null,
      "etag": "13cff662fe9d2218ae8b73ff05c1f653",
      "created_by": {
        "access_key": "462313613892389",
        "custom_id": "gaga.binx@gmail.com",
        "external_id": "551bcab9372d004621842d78700916"
      },
      "uploaded_by": {
        "access_key": "462313613892389",
        "custom_id": "gaga.binx@gmail.com",
        "external_id": "551bcab9372d004621842d78700916"
      }
    },
    {
      "asset_id": "c34612e61610d69edf88f35b7cdcd044",
      "public_id": "My Photos/Rori_contortions-040-200329_x0kzs6",
      "folder": "My Photos",
      "filename": "Rori_contortions-040-200329_x0kzs6",
      "display_name": "Rori_contortions-040-200329_x0kzs6",
      "format": "jpg",
      "version": 1635499190,
      "resource_type": "image",
      "type": "upload",
      "created_at": "2021-10-29T09:19:50+00:00",
      "uploaded_at": "2021-10-29T09:19:50+00:00",
      "bytes": 7839792,
      "backup_bytes": 0,
      "width": 3560,
      "height": 5340,
      "aspect_ratio": 0.66667,
      "pixels": 19010400,
      "url": "http://res.cloudinary.com/milliegrey/image/upload/v1635499190/My%20Photos/Rori_contortions-040-200329_x0kzs6.jpg",
      "secure_url": "https://res.cloudinary.com/milliegrey/image/upload/v1635499190/My%20Photos/Rori_contortions-040-200329_x0kzs6.jpg",
      "status": "active",
      "access_mode": "public",
      "access_control": null,
      "etag": "9f9f5d1abb9eaa8b23ebc5b57b79abbc",
      "created_by": {
        "access_key": "462313613892389",
        "custom_id": "gaga.binx@gmail.com",
        "external_id": "551bcab9372d004621842d78700916"
      },
      "uploaded_by": {
        "access_key": "462313613892389",
        "custom_id": "gaga.binx@gmail.com",
        "external_id": "551bcab9372d004621842d78700916"
      }
    },
    {
      "asset_id": "e241b45f41caf815b71ce48c6bd9d7cf",
      "public_id": "My Photos/ryes_23rd-025-180421_kohmfk",
      "folder": "My Photos",
      "filename": "ryes_23rd-025-180421_kohmfk",
      "display_name": "ryes_23rd-025-180421_kohmfk",
      "format": "jpg",
      "version": 1635499190,
      "resource_type": "image",
      "type": "upload",
      "created_at": "2021-10-29T09:19:50+00:00",
      "uploaded_at": "2021-10-29T09:19:50+00:00",
      "bytes": 3338747,
      "backup_bytes": 0,
      "width": 2176,
      "height": 3264,
      "aspect_ratio": 0.66667,
      "pixels": 7102464,
      "url": "http://res.cloudinary.com/milliegrey/image/upload/v1635499190/My%20Photos/ryes_23rd-025-180421_kohmfk.jpg",
      "secure_url": "https://res.cloudinary.com/milliegrey/image/upload/v1635499190/My%20Photos/ryes_23rd-025-180421_kohmfk.jpg",
      "status": "active",
      "access_mode": "public",
      "access_control": null,
      "etag": "de9b5e3e733408e4a28000210466f405",
      "created_by": {
        "access_key": "462313613892389",
        "custom_id": "gaga.binx@gmail.com",
        "external_id": "551bcab9372d004621842d78700916"
      },
      "uploaded_by": {
        "access_key": "462313613892389",
        "custom_id": "gaga.binx@gmail.com",
        "external_id": "551bcab9372d004621842d78700916"
      }
    },
    {
      "asset_id": "923d6f7fc1c71e544560c2ed792b7d9b",
      "public_id": "My Photos/Rori_contortions-090-200329_zzifpp",
      "folder": "My Photos",
      "filename": "Rori_contortions-090-200329_zzifpp",
      "display_name": "Rori_contortions-090-200329_zzifpp",
      "format": "jpg",
      "version": 1635499189,
      "resource_type": "image",
      "type": "upload",
      "created_at": "2021-10-29T09:19:49+00:00",
      "uploaded_at": "2021-10-29T09:19:49+00:00",
      "bytes": 7506820,
      "backup_bytes": 0,
      "width": 3787,
      "height": 5680,
      "aspect_ratio": 0.66673,
      "pixels": 21510160,
      "url": "http://res.cloudinary.com/milliegrey/image/upload/v1635499189/My%20Photos/Rori_contortions-090-200329_zzifpp.jpg",
      "secure_url": "https://res.cloudinary.com/milliegrey/image/upload/v1635499189/My%20Photos/Rori_contortions-090-200329_zzifpp.jpg",
      "status": "active",
      "access_mode": "public",
      "access_control": null,
      "etag": "315f37a319ae1485a2c1d7c1e96fd352",
      "created_by": {
        "access_key": "462313613892389",
        "custom_id": "gaga.binx@gmail.com",
        "external_id": "551bcab9372d004621842d78700916"
      },
      "uploaded_by": {
        "access_key": "462313613892389",
        "custom_id": "gaga.binx@gmail.com",
        "external_id": "551bcab9372d004621842d78700916"
      }
    },
    {
      "asset_id": "d7aa320052e143696fb17ed2b4ef0164",
      "public_id": "My Photos/Rori_contortions-074-200329_ivczzz",
      "folder": "My Photos",
      "filename": "Rori_contortions-074-200329_ivczzz",
      "display_name": "Rori_contortions-074-200329_ivczzz",
      "format": "jpg",
      "version": 1635499189,
      "resource_type": "image",
      "type": "upload",
      "created_at": "2021-10-29T09:19:49+00:00",
      "uploaded_at": "2021-10-29T09:19:49+00:00",
      "bytes": 7249505,
      "backup_bytes": 0,
      "width": 3665,
      "height": 5498,
      "aspect_ratio": 0.66661,
      "pixels": 20150170,
      "url": "http://res.cloudinary.com/milliegrey/image/upload/v1635499189/My%20Photos/Rori_contortions-074-200329_ivczzz.jpg",
      "secure_url": "https://res.cloudinary.com/milliegrey/image/upload/v1635499189/My%20Photos/Rori_contortions-074-200329_ivczzz.jpg",
      "status": "active",
      "access_mode": "public",
      "access_control": null,
      "etag": "0a3fa74a0a87e80c199ae62978b9d71d",
      "created_by": {
        "access_key": "462313613892389",
        "custom_id": "gaga.binx@gmail.com",
        "external_id": "551bcab9372d004621842d78700916"
      },
      "uploaded_by": {
        "access_key": "462313613892389",
        "custom_id": "gaga.binx@gmail.com",
        "external_id": "551bcab9372d004621842d78700916"
      }
    },
    {
      "asset_id": "91ec6e7f06209b91c4fbc7118eaec971",
      "public_id": "My Photos/beccasParty-048-211008_m1cfbw",
      "folder": "My Photos",
      "filename": "beccasParty-048-211008_m1cfbw",
      "display_name": "beccasParty-048-211008_m1cfbw",
      "format": "jpg",
      "version": 1635499188,
      "resource_type": "image",
      "type": "upload",
      "created_at": "2021-10-29T09:19:48+00:00",
      "uploaded_at": "2021-10-29T09:19:48+00:00",
      "bytes": 9204731,
      "backup_bytes": 0,
      "width": 3264,
      "height": 4896,
      "aspect_ratio": 0.66667,
      "pixels": 15980544,
      "url": "http://res.cloudinary.com/milliegrey/image/upload/v1635499188/My%20Photos/beccasParty-048-211008_m1cfbw.jpg",
      "secure_url": "https://res.cloudinary.com/milliegrey/image/upload/v1635499188/My%20Photos/beccasParty-048-211008_m1cfbw.jpg",
      "status": "active",
      "access_mode": "public",
      "access_control": null,
      "etag": "b6d2aba876d8de6f350244b28ece943e",
      "created_by": {
        "access_key": "462313613892389",
        "custom_id": "gaga.binx@gmail.com",
        "external_id": "551bcab9372d004621842d78700916"
      },
      "uploaded_by": {
        "access_key": "462313613892389",
        "custom_id": "gaga.binx@gmail.com",
        "external_id": "551bcab9372d004621842d78700916"
      }
    },
    {
      "asset_id": "fcc82a3212a675b50a035a1359caeb88",
      "public_id": "My Photos/Rori_contortions-052-200329_nnemwf",
      "folder": "My Photos",
      "filename": "Rori_contortions-052-200329_nnemwf",
      "display_name": "Rori_contortions-052-200329_nnemwf",
      "format": "jpg",
      "version": 1635499188,
      "resource_type": "image",
      "type": "upload",
      "created_at": "2021-10-29T09:19:48+00:00",
      "uploaded_at": "2021-10-29T09:19:48+00:00",
      "bytes": 6166098,
      "backup_bytes": 0,
      "width": 3351,
      "height": 5027,
      "aspect_ratio": 0.6666,
      "pixels": 16845477,
      "url": "http://res.cloudinary.com/milliegrey/image/upload/v1635499188/My%20Photos/Rori_contortions-052-200329_nnemwf.jpg",
      "secure_url": "https://res.cloudinary.com/milliegrey/image/upload/v1635499188/My%20Photos/Rori_contortions-052-200329_nnemwf.jpg",
      "status": "active",
      "access_mode": "public",
      "access_control": null,
      "etag": "680d381ea66af6288b2ef19e2c10ec07",
      "created_by": {
        "access_key": "462313613892389",
        "custom_id": "gaga.binx@gmail.com",
        "external_id": "551bcab9372d004621842d78700916"
      },
      "uploaded_by": {
        "access_key": "462313613892389",
        "custom_id": "gaga.binx@gmail.com",
        "external_id": "551bcab9372d004621842d78700916"
      }
    },
    {
      "asset_id": "03487e48c237452b0a1c3e916b3892c9",
      "public_id": "My Photos/Rori_contortions-039-200329_jfmbsy",
      "folder": "My Photos",
      "filename": "Rori_contortions-039-200329_jfmbsy",
      "display_name": "Rori_contortions-039-200329_jfmbsy",
      "format": "jpg",
      "version": 1635499187,
      "resource_type": "image",
      "type": "upload",
      "created_at": "2021-10-29T09:19:47+00:00",
      "uploaded_at": "2021-10-29T09:19:47+00:00",
      "bytes": 5806162,
      "backup_bytes": 0,
      "width": 4591,
      "height": 3061,
      "aspect_ratio": 1.49984,
      "pixels": 14053051,
      "url": "http://res.cloudinary.com/milliegrey/image/upload/v1635499187/My%20Photos/Rori_contortions-039-200329_jfmbsy.jpg",
      "secure_url": "https://res.cloudinary.com/milliegrey/image/upload/v1635499187/My%20Photos/Rori_contortions-039-200329_jfmbsy.jpg",
      "status": "active",
      "access_mode": "public",
      "access_control": null,
      "etag": "a99425d6d1d1e502cd6b077d680fe5af",
      "created_by": {
        "access_key": "462313613892389",
        "custom_id": "gaga.binx@gmail.com",
        "external_id": "551bcab9372d004621842d78700916"
      },
      "uploaded_by": {
        "access_key": "462313613892389",
        "custom_id": "gaga.binx@gmail.com",
        "external_id": "551bcab9372d004621842d78700916"
      }
    },
    {
      "asset_id": "b520fb85bae2add07c435a7f859c144e",
      "public_id": "My Photos/mills-untitled_shoot-652-211019_yyn77q",
      "folder": "My Photos",
      "filename": "mills-untitled_shoot-652-211019_yyn77q",
      "display_name": "mills-untitled_shoot-652-211019_yyn77q",
      "format": "jpg",
      "version": 1635499186,
      "resource_type": "image",
      "type": "upload",
      "created_at": "2021-10-29T09:19:46+00:00",
      "uploaded_at": "2021-10-29T09:19:46+00:00",
      "bytes": 8305340,
      "backup_bytes": 0,
      "width": 4896,
      "height": 3264,
      "aspect_ratio": 1.5,
      "pixels": 15980544,
      "url": "http://res.cloudinary.com/milliegrey/image/upload/v1635499186/My%20Photos/mills-untitled_shoot-652-211019_yyn77q.jpg",
      "secure_url": "https://res.cloudinary.com/milliegrey/image/upload/v1635499186/My%20Photos/mills-untitled_shoot-652-211019_yyn77q.jpg",
      "status": "active",
      "access_mode": "public",
      "access_control": null,
      "etag": "c03418ada1ebcaf131be7cd3d95d3a47",
      "created_by": {
        "access_key": "462313613892389",
        "custom_id": "gaga.binx@gmail.com",
        "external_id": "551bcab9372d004621842d78700916"
      },
      "uploaded_by": {
        "access_key": "462313613892389",
        "custom_id": "gaga.binx@gmail.com",
        "external_id": "551bcab9372d004621842d78700916"
      }
    },
    {
      "asset_id": "0ed854bed7f489117bfda747cb9b64a5",
      "public_id": "My Photos/untitled_shoot-066-210925_iapdqs",
      "folder": "My Photos",
      "filename": "untitled_shoot-066-210925_iapdqs",
      "display_name": "untitled_shoot-066-210925_iapdqs",
      "format": "jpg",
      "version": 1635499186,
      "resource_type": "image",
      "type": "upload",
      "created_at": "2021-10-29T09:19:46+00:00",
      "uploaded_at": "2021-10-29T09:19:46+00:00",
      "bytes": 6822872,
      "backup_bytes": 0,
      "width": 3264,
      "height": 4896,
      "aspect_ratio": 0.66667,
      "pixels": 15980544,
      "url": "http://res.cloudinary.com/milliegrey/image/upload/v1635499186/My%20Photos/untitled_shoot-066-210925_iapdqs.jpg",
      "secure_url": "https://res.cloudinary.com/milliegrey/image/upload/v1635499186/My%20Photos/untitled_shoot-066-210925_iapdqs.jpg",
      "status": "active",
      "access_mode": "public",
      "access_control": null,
      "etag": "8418eeda542868c5166dbb604747e221",
      "created_by": {
        "access_key": "462313613892389",
        "custom_id": "gaga.binx@gmail.com",
        "external_id": "551bcab9372d004621842d78700916"
      },
      "uploaded_by": {
        "access_key": "462313613892389",
        "custom_id": "gaga.binx@gmail.com",
        "external_id": "551bcab9372d004621842d78700916"
      }
    },
    {
      "asset_id": "7f399e4fdb331338154a005a3332275c",
      "public_id": "My Photos/MakeupAnnaGoodstuff-256-170727_zx4apz",
      "folder": "My Photos",
      "filename": "MakeupAnnaGoodstuff-256-170727_zx4apz",
      "display_name": "MakeupAnnaGoodstuff-256-170727_zx4apz",
      "format": "jpg",
      "version": 1635499185,
      "resource_type": "image",
      "type": "upload",
      "created_at": "2021-10-29T09:19:45+00:00",
      "uploaded_at": "2021-10-29T09:19:45+00:00",
      "bytes": 284384,
      "backup_bytes": 0,
      "width": 1672,
      "height": 717,
      "aspect_ratio": 2.33194,
      "pixels": 1198824,
      "url": "http://res.cloudinary.com/milliegrey/image/upload/v1635499185/My%20Photos/MakeupAnnaGoodstuff-256-170727_zx4apz.jpg",
      "secure_url": "https://res.cloudinary.com/milliegrey/image/upload/v1635499185/My%20Photos/MakeupAnnaGoodstuff-256-170727_zx4apz.jpg",
      "status": "active",
      "access_mode": "public",
      "access_control": null,
      "etag": "01512a1d99707697b0eb52bbd46d85a1",
      "created_by": {
        "access_key": "462313613892389",
        "custom_id": "gaga.binx@gmail.com",
        "external_id": "551bcab9372d004621842d78700916"
      },
      "uploaded_by": {
        "access_key": "462313613892389",
        "custom_id": "gaga.binx@gmail.com",
        "external_id": "551bcab9372d004621842d78700916"
      }
    },
    {
      "asset_id": "56ba30bbee708ab8a4edee95ceb38f9f",
      "public_id": "My Photos/untitled_shoot-018-210925_h9d8np",
      "folder": "My Photos",
      "filename": "untitled_shoot-018-210925_h9d8np",
      "display_name": "untitled_shoot-018-210925_h9d8np",
      "format": "jpg",
      "version": 1635499185,
      "resource_type": "image",
      "type": "upload",
      "created_at": "2021-10-29T09:19:45+00:00",
      "uploaded_at": "2021-10-29T09:19:45+00:00",
      "bytes": 6228652,
      "backup_bytes": 0,
      "width": 3264,
      "height": 4896,
      "aspect_ratio": 0.66667,
      "pixels": 15980544,
      "url": "http://res.cloudinary.com/milliegrey/image/upload/v1635499185/My%20Photos/untitled_shoot-018-210925_h9d8np.jpg",
      "secure_url": "https://res.cloudinary.com/milliegrey/image/upload/v1635499185/My%20Photos/untitled_shoot-018-210925_h9d8np.jpg",
      "status": "active",
      "access_mode": "public",
      "access_control": null,
      "etag": "6985352d6bfc9e34205a972fcef574c2",
      "created_by": {
        "access_key": "462313613892389",
        "custom_id": "gaga.binx@gmail.com",
        "external_id": "551bcab9372d004621842d78700916"
      },
      "uploaded_by": {
        "access_key": "462313613892389",
        "custom_id": "gaga.binx@gmail.com",
        "external_id": "551bcab9372d004621842d78700916"
      }
    },
    {
      "asset_id": "6c09a4fff29a71bff06ac6576999bbc5",
      "public_id": "My Photos/untitled_shoot-028-210925_zjprju",
      "folder": "My Photos",
      "filename": "untitled_shoot-028-210925_zjprju",
      "display_name": "untitled_shoot-028-210925_zjprju",
      "format": "jpg",
      "version": 1635499184,
      "resource_type": "image",
      "type": "upload",
      "created_at": "2021-10-29T09:19:44+00:00",
      "uploaded_at": "2021-10-29T09:19:44+00:00",
      "bytes": 4229070,
      "backup_bytes": 0,
      "width": 4117,
      "height": 2745,
      "aspect_ratio": 1.49982,
      "pixels": 11301165,
      "url": "http://res.cloudinary.com/milliegrey/image/upload/v1635499184/My%20Photos/untitled_shoot-028-210925_zjprju.jpg",
      "secure_url": "https://res.cloudinary.com/milliegrey/image/upload/v1635499184/My%20Photos/untitled_shoot-028-210925_zjprju.jpg",
      "status": "active",
      "access_mode": "public",
      "access_control": null,
      "etag": "5c9a018b237056254586935c09fc97dc",
      "created_by": {
        "access_key": "462313613892389",
        "custom_id": "gaga.binx@gmail.com",
        "external_id": "551bcab9372d004621842d78700916"
      },
      "uploaded_by": {
        "access_key": "462313613892389",
        "custom_id": "gaga.binx@gmail.com",
        "external_id": "551bcab9372d004621842d78700916"
      }
    },
    {
      "asset_id": "9466582f611b796d51807ca26f310d96",
      "public_id": "My Photos/mills-untitled_shoot-007-211024_f8q7sr",
      "folder": "My Photos",
      "filename": "mills-untitled_shoot-007-211024_f8q7sr",
      "display_name": "mills-untitled_shoot-007-211024_f8q7sr",
      "format": "jpg",
      "version": 1635499184,
      "resource_type": "image",
      "type": "upload",
      "created_at": "2021-10-29T09:19:44+00:00",
      "uploaded_at": "2021-10-29T09:19:44+00:00",
      "bytes": 4963776,
      "backup_bytes": 0,
      "width": 4896,
      "height": 3264,
      "aspect_ratio": 1.5,
      "pixels": 15980544,
      "url": "http://res.cloudinary.com/milliegrey/image/upload/v1635499184/My%20Photos/mills-untitled_shoot-007-211024_f8q7sr.jpg",
      "secure_url": "https://res.cloudinary.com/milliegrey/image/upload/v1635499184/My%20Photos/mills-untitled_shoot-007-211024_f8q7sr.jpg",
      "status": "active",
      "access_mode": "public",
      "access_control": null,
      "etag": "39d83e28e12b7efbdad305bd52d8942c",
      "created_by": {
        "access_key": "462313613892389",
        "custom_id": "gaga.binx@gmail.com",
        "external_id": "551bcab9372d004621842d78700916"
      },
      "uploaded_by": {
        "access_key": "462313613892389",
        "custom_id": "gaga.binx@gmail.com",
        "external_id": "551bcab9372d004621842d78700916"
      }
    },
    {
      "asset_id": "d8f6ddfbf9d25be67a378d4ff48ae6a0",
      "public_id": "My Photos/untitled_shoot-010-210924-HDR_x7qvrf",
      "folder": "My Photos",
      "filename": "untitled_shoot-010-210924-HDR_x7qvrf",
      "display_name": "untitled_shoot-010-210924-HDR_x7qvrf",
      "format": "jpg",
      "version": 1635499184,
      "resource_type": "image",
      "type": "upload",
      "created_at": "2021-10-29T09:19:44+00:00",
      "uploaded_at": "2021-10-29T09:19:44+00:00",
      "bytes": 4555257,
      "backup_bytes": 0,
      "width": 4770,
      "height": 2554,
      "aspect_ratio": 1.86766,
      "pixels": 12182580,
      "url": "http://res.cloudinary.com/milliegrey/image/upload/v1635499184/My%20Photos/untitled_shoot-010-210924-HDR_x7qvrf.jpg",
      "secure_url": "https://res.cloudinary.com/milliegrey/image/upload/v1635499184/My%20Photos/untitled_shoot-010-210924-HDR_x7qvrf.jpg",
      "status": "active",
      "access_mode": "public",
      "access_control": null,
      "etag": "6a32016110bbab6be042862b0a3ec6a3",
      "created_by": {
        "access_key": "462313613892389",
        "custom_id": "gaga.binx@gmail.com",
        "external_id": "551bcab9372d004621842d78700916"
      },
      "uploaded_by": {
        "access_key": "462313613892389",
        "custom_id": "gaga.binx@gmail.com",
        "external_id": "551bcab9372d004621842d78700916"
      }
    },
    {
      "asset_id": "1f323b1b250f76ea7f1828e305d103e5",
      "public_id": "My Photos/perseids_with_anna-005-170813_ss0htt",
      "folder": "My Photos",
      "filename": "perseids_with_anna-005-170813_ss0htt",
      "display_name": "perseids_with_anna-005-170813_ss0htt",
      "format": "jpg",
      "version": 1635499183,
      "resource_type": "image",
      "type": "upload",
      "created_at": "2021-10-29T09:19:43+00:00",
      "uploaded_at": "2021-10-29T09:19:43+00:00",
      "bytes": 2079830,
      "backup_bytes": 0,
      "width": 6000,
      "height": 4000,
      "aspect_ratio": 1.5,
      "pixels": 24000000,
      "url": "http://res.cloudinary.com/milliegrey/image/upload/v1635499183/My%20Photos/perseids_with_anna-005-170813_ss0htt.jpg",
      "secure_url": "https://res.cloudinary.com/milliegrey/image/upload/v1635499183/My%20Photos/perseids_with_anna-005-170813_ss0htt.jpg",
      "status": "active",
      "access_mode": "public",
      "access_control": null,
      "etag": "efbc6ecc788d46ba055dd9f8cbcd1c62",
      "created_by": {
        "access_key": "462313613892389",
        "custom_id": "gaga.binx@gmail.com",
        "external_id": "551bcab9372d004621842d78700916"
      },
      "uploaded_by": {
        "access_key": "462313613892389",
        "custom_id": "gaga.binx@gmail.com",
        "external_id": "551bcab9372d004621842d78700916"
      }
    },
    {
      "asset_id": "2608932c403d88704386344ae5cf789c",
      "public_id": "samples/elephants",
      "folder": "samples",
      "filename": "elephants",
      "display_name": null,
      "format": "mp4",
      "version": 1635454201,
      "resource_type": "video",
      "type": "upload",
      "created_at": "2021-10-28T20:50:01+00:00",
      "uploaded_at": "2021-10-28T20:50:01+00:00",
      "bytes": 38855178,
      "backup_bytes": 0,
      "width": 1920,
      "height": 1080,
      "aspect_ratio": 1.77778,
      "pixels": 2073600,
      "duration": 48.515182,
      "pages": 0,
      "url": "http://res.cloudinary.com/milliegrey/video/upload/v1635454201/samples/elephants.mp4",
      "secure_url": "https://res.cloudinary.com/milliegrey/video/upload/v1635454201/samples/elephants.mp4",
      "status": "active",
      "access_mode": "public",
      "access_control": null,
      "etag": "ab10c05c859968836ff46b80c7733ad7",
      "created_by": null,
      "uploaded_by": null
    },
    {
      "asset_id": "9ec3046e722e7fc41d171cfe6ffb72e4",
      "public_id": "samples/sea-turtle",
      "folder": "samples",
      "filename": "sea-turtle",
      "display_name": null,
      "format": "mp4",
      "version": 1635454199,
      "resource_type": "video",
      "type": "upload",
      "created_at": "2021-10-28T20:49:59+00:00",
      "uploaded_at": "2021-10-28T20:49:59+00:00",
      "bytes": 27932506,
      "backup_bytes": 0,
      "width": 1920,
      "height": 1080,
      "aspect_ratio": 1.77778,
      "pixels": 2073600,
      "duration": 15.215215,
      "pages": 0,
      "url": "http://res.cloudinary.com/milliegrey/video/upload/v1635454199/samples/sea-turtle.mp4",
      "secure_url": "https://res.cloudinary.com/milliegrey/video/upload/v1635454199/samples/sea-turtle.mp4",
      "status": "active",
      "access_mode": "public",
      "access_control": null,
      "etag": "dd4c2249ae24f78685786c82917e7cb0",
      "created_by": null,
      "uploaded_by": null
    },
    {
      "asset_id": "00ff2b863b0f1906f4f92a6f6d3f1263",
      "public_id": "samples/landscapes/landscape-panorama",
      "folder": "samples/landscapes",
      "filename": "landscape-panorama",
      "display_name": null,
      "format": "jpg",
      "version": 1635454198,
      "resource_type": "image",
      "type": "upload",
      "created_at": "2021-10-28T20:49:58+00:00",
      "uploaded_at": "2021-10-28T20:49:58+00:00",
      "bytes": 7858062,
      "backup_bytes": 0,
      "width": 10906,
      "height": 2349,
      "aspect_ratio": 4.64283,
      "pixels": 25618194,
      "url": "http://res.cloudinary.com/milliegrey/image/upload/v1635454198/samples/landscapes/landscape-panorama.jpg",
      "secure_url": "https://res.cloudinary.com/milliegrey/image/upload/v1635454198/samples/landscapes/landscape-panorama.jpg",
      "status": "active",
      "access_mode": "public",
      "access_control": null,
      "etag": "5eae5b5f619fa226b724a3d75afe4b7d",
      "created_by": null,
      "uploaded_by": null
    },
    {
      "asset_id": "0bb2e6fe4af2e4c2dcc07aee232c5ca7",
      "public_id": "samples/animals/kitten-playing",
      "folder": "samples/animals",
      "filename": "kitten-playing",
      "display_name": null,
      "format": "gif",
      "version": 1635454196,
      "resource_type": "image",
      "type": "upload",
      "created_at": "2021-10-28T20:49:56+00:00",
      "uploaded_at": "2021-10-28T20:49:56+00:00",
      "bytes": 6620002,
      "backup_bytes": 0,
      "width": 320,
      "height": 180,
      "aspect_ratio": 1.77778,
      "pixels": 57600,
      "pages": 140,
      "url": "http://res.cloudinary.com/milliegrey/image/upload/v1635454196/samples/animals/kitten-playing.gif",
      "secure_url": "https://res.cloudinary.com/milliegrey/image/upload/v1635454196/samples/animals/kitten-playing.gif",
      "status": "active",
      "access_mode": "public",
      "access_control": null,
      "etag": "94483f5475a69adef10a0c4628a72215",
      "created_by": null,
      "uploaded_by": null
    },
    {
      "asset_id": "a6ed540a81fcbd22b1abfd62dfb134e3",
      "public_id": "samples/landscapes/nature-mountains",
      "folder": "samples/landscapes",
      "filename": "nature-mountains",
      "display_name": null,
      "format": "jpg",
      "version": 1635454195,
      "resource_type": "image",
      "type": "upload",
      "created_at": "2021-10-28T20:49:55+00:00",
      "uploaded_at": "2021-10-28T20:49:55+00:00",
      "bytes": 3171453,
      "backup_bytes": 0,
      "width": 3000,
      "height": 2000,
      "aspect_ratio": 1.5,
      "pixels": 6000000,
      "url": "http://res.cloudinary.com/milliegrey/image/upload/v1635454195/samples/landscapes/nature-mountains.jpg",
      "secure_url": "https://res.cloudinary.com/milliegrey/image/upload/v1635454195/samples/landscapes/nature-mountains.jpg",
      "status": "active",
      "access_mode": "public",
      "access_control": null,
      "etag": "1930edf19b8185f34b6ec0b0aefd6d9f",
      "created_by": null,
      "uploaded_by": null
    },
    {
      "asset_id": "ecc8a9b0d54e2f55528ba8ee0c661b06",
      "public_id": "samples/cloudinary-group",
      "folder": "samples",
      "filename": "cloudinary-group",
      "display_name": null,
      "format": "jpg",
      "version": 1635454194,
      "resource_type": "image",
      "type": "upload",
      "created_at": "2021-10-28T20:49:54+00:00",
      "uploaded_at": "2021-10-28T20:49:54+00:00",
      "bytes": 2856169,
      "backup_bytes": 0,
      "width": 3000,
      "height": 1526,
      "aspect_ratio": 1.96592,
      "pixels": 4578000,
      "url": "http://res.cloudinary.com/milliegrey/image/upload/v1635454194/samples/cloudinary-group.jpg",
      "secure_url": "https://res.cloudinary.com/milliegrey/image/upload/v1635454194/samples/cloudinary-group.jpg",
      "status": "active",
      "access_mode": "public",
      "access_control": null,
      "etag": "4d3a915d4bbe34300d29c9c5f90a9d7c",
      "created_by": null,
      "uploaded_by": null
    },
    {
      "asset_id": "1167482f7110e289db330a6ff131af37",
      "public_id": "samples/food/spices",
      "folder": "samples/food",
      "filename": "spices",
      "display_name": null,
      "format": "jpg",
      "version": 1635454194,
      "resource_type": "image",
      "type": "upload",
      "created_at": "2021-10-28T20:49:54+00:00",
      "uploaded_at": "2021-10-28T20:49:54+00:00",
      "bytes": 2129950,
      "backup_bytes": 0,
      "width": 2000,
      "height": 2000,
      "aspect_ratio": 1.0,
      "pixels": 4000000,
      "url": "http://res.cloudinary.com/milliegrey/image/upload/v1635454194/samples/food/spices.jpg",
      "secure_url": "https://res.cloudinary.com/milliegrey/image/upload/v1635454194/samples/food/spices.jpg",
      "status": "active",
      "access_mode": "public",
      "access_control": null,
      "etag": "104f9ba6d7a2cfe6bde69e2c0cdd4099",
      "created_by": null,
      "uploaded_by": null
    },
    {
      "asset_id": "8f02d96184eb4f226cb6ba993d548f2d",
      "public_id": "samples/imagecon-group",
      "folder": "samples",
      "filename": "imagecon-group",
      "display_name": null,
      "format": "jpg",
      "version": 1635454193,
      "resource_type": "image",
      "type": "upload",
      "created_at": "2021-10-28T20:49:53+00:00",
      "uploaded_at": "2021-10-28T20:49:53+00:00",
      "bytes": 1487070,
      "backup_bytes": 0,
      "width": 2800,
      "height": 1867,
      "aspect_ratio": 1.49973,
      "pixels": 5227600,
      "url": "http://res.cloudinary.com/milliegrey/image/upload/v1635454193/samples/imagecon-group.jpg",
      "secure_url": "https://res.cloudinary.com/milliegrey/image/upload/v1635454193/samples/imagecon-group.jpg",
      "status": "active",
      "access_mode": "public",
      "access_control": null,
      "etag": "b6076e617f243f46baa55d1a29e51b74",
      "created_by": null,
      "uploaded_by": null
    },
    {
      "asset_id": "c20d20887dfc6fee69447493856da83b",
      "public_id": "samples/ecommerce/accessories-bag",
      "folder": "samples/ecommerce",
      "filename": "accessories-bag",
      "display_name": null,
      "format": "jpg",
      "version": 1635454192,
      "resource_type": "image",
      "type": "upload",
      "created_at": "2021-10-28T20:49:52+00:00",
      "uploaded_at": "2021-10-28T20:49:52+00:00",
      "bytes": 1459256,
      "backup_bytes": 0,
      "width": 3000,
      "height": 2000,
      "aspect_ratio": 1.5,
      "pixels": 6000000,
      "url": "http://res.cloudinary.com/milliegrey/image/upload/v1635454192/samples/ecommerce/accessories-bag.jpg",
      "secure_url": "https://res.cloudinary.com/milliegrey/image/upload/v1635454192/samples/ecommerce/accessories-bag.jpg",
      "status": "active",
      "access_mode": "public",
      "access_control": null,
      "etag": "a53cee7a32aabe5e9ec02bfc358e89a3",
      "created_by": null,
      "uploaded_by": null
    },
    {
      "asset_id": "4576af9f12498535b99753b527e15e07",
      "public_id": "samples/ecommerce/leather-bag-gray",
      "folder": "samples/ecommerce",
      "filename": "leather-bag-gray",
      "display_name": null,
      "format": "jpg",
      "version": 1635454192,
      "resource_type": "image",
      "type": "upload",
      "created_at": "2021-10-28T20:49:52+00:00",
      "uploaded_at": "2021-10-28T20:49:52+00:00",
      "bytes": 1323582,
      "backup_bytes": 0,
      "width": 2385,
      "height": 1590,
      "aspect_ratio": 1.5,
      "pixels": 3792150,
      "url": "http://res.cloudinary.com/milliegrey/image/upload/v1635454192/samples/ecommerce/leather-bag-gray.jpg",
      "secure_url": "https://res.cloudinary.com/milliegrey/image/upload/v1635454192/samples/ecommerce/leather-bag-gray.jpg",
      "status": "active",
      "access_mode": "public",
      "access_control": null,
      "etag": "a9a77c2b232fe57385ddd204bbb46749",
      "created_by": null,
      "uploaded_by": null
    },
    {
      "asset_id": "2cb5b5305b4512838346cdc4f9602072",
      "public_id": "samples/ecommerce/car-interior-design",
      "folder": "samples/ecommerce",
      "filename": "car-interior-design",
      "display_name": null,
      "format": "jpg",
      "version": 1635454192,
      "resource_type": "image",
      "type": "upload",
      "created_at": "2021-10-28T20:49:52+00:00",
      "uploaded_at": "2021-10-28T20:49:52+00:00",
      "bytes": 1254103,
      "backup_bytes": 0,
      "width": 2000,
      "height": 2667,
      "aspect_ratio": 0.74991,
      "pixels": 5334000,
      "url": "http://res.cloudinary.com/milliegrey/image/upload/v1635454192/samples/ecommerce/car-interior-design.jpg",
      "secure_url": "https://res.cloudinary.com/milliegrey/image/upload/v1635454192/samples/ecommerce/car-interior-design.jpg",
      "status": "active",
      "access_mode": "public",
      "access_control": null,
      "etag": "053f13b87786adaf2ba63b4c6af8e40b",
      "created_by": null,
      "uploaded_by": null
    },
    {
      "asset_id": "f8ceec996a38f4b4b047628197f3b1a6",
      "public_id": "samples/landscapes/beach-boat",
      "folder": "samples/landscapes",
      "filename": "beach-boat",
      "display_name": null,
      "format": "jpg",
      "version": 1635454191,
      "resource_type": "image",
      "type": "upload",
      "created_at": "2021-10-28T20:49:51+00:00",
      "uploaded_at": "2021-10-28T20:49:51+00:00",
      "bytes": 1235823,
      "backup_bytes": 0,
      "width": 2600,
      "height": 1950,
      "aspect_ratio": 1.33333,
      "pixels": 5070000,
      "url": "http://res.cloudinary.com/milliegrey/image/upload/v1635454191/samples/landscapes/beach-boat.jpg",
      "secure_url": "https://res.cloudinary.com/milliegrey/image/upload/v1635454191/samples/landscapes/beach-boat.jpg",
      "status": "active",
      "access_mode": "public",
      "access_control": null,
      "etag": "923f6e7b5e51736ca42fc228cea0c24e",
      "created_by": null,
      "uploaded_by": null
    },
    {
      "asset_id": "bcdb96873dda7404526fcb53d157d559",
      "public_id": "samples/people/bicycle",
      "folder": "samples/people",
      "filename": "bicycle",
      "display_name": null,
      "format": "jpg",
      "version": 1635454191,
      "resource_type": "image",
      "type": "upload",
      "created_at": "2021-10-28T20:49:51+00:00",
      "uploaded_at": "2021-10-28T20:49:51+00:00",
      "bytes": 1130015,
      "backup_bytes": 0,
      "width": 2889,
      "height": 1926,
      "aspect_ratio": 1.5,
      "pixels": 5564214,
      "url": "http://res.cloudinary.com/milliegrey/image/upload/v1635454191/samples/people/bicycle.jpg",
      "secure_url": "https://res.cloudinary.com/milliegrey/image/upload/v1635454191/samples/people/bicycle.jpg",
      "status": "active",
      "access_mode": "public",
      "access_control": null,
      "etag": "e4ee027bcf27b9c639cbdf0e91dc3b00",
      "created_by": null,
      "uploaded_by": null
    },
    {
      "asset_id": "c5cbc584a63f7d688480fe012d6972e9",
      "public_id": "samples/landscapes/architecture-signs",
      "folder": "samples/landscapes",
      "filename": "architecture-signs",
      "display_name": null,
      "format": "jpg",
      "version": 1635454190,
      "resource_type": "image",
      "type": "upload",
      "created_at": "2021-10-28T20:49:50+00:00",
      "uploaded_at": "2021-10-28T20:49:50+00:00",
      "bytes": 945255,
      "backup_bytes": 0,
      "width": 3000,
      "height": 2000,
      "aspect_ratio": 1.5,
      "pixels": 6000000,
      "url": "http://res.cloudinary.com/milliegrey/image/upload/v1635454190/samples/landscapes/architecture-signs.jpg",
      "secure_url": "https://res.cloudinary.com/milliegrey/image/upload/v1635454190/samples/landscapes/architecture-signs.jpg",
      "status": "active",
      "access_mode": "public",
      "access_control": null,
      "etag": "52eebe8be03f1141112ebcac43cd8861",
      "created_by": null,
      "uploaded_by": null
    },
    {
      "asset_id": "142aa8a34f69b0e584a7b3499fbc79d6",
      "public_id": "samples/animals/three-dogs",
      "folder": "samples/animals",
      "filename": "three-dogs",
      "display_name": null,
      "format": "jpg",
      "version": 1635454190,
      "resource_type": "image",
      "type": "upload",
      "created_at": "2021-10-28T20:49:50+00:00",
      "uploaded_at": "2021-10-28T20:49:50+00:00",
      "bytes": 854929,
      "backup_bytes": 0,
      "width": 2700,
      "height": 1800,
      "aspect_ratio": 1.5,
      "pixels": 4860000,
      "url": "http://res.cloudinary.com/milliegrey/image/upload/v1635454190/samples/animals/three-dogs.jpg",
      "secure_url": "https://res.cloudinary.com/milliegrey/image/upload/v1635454190/samples/animals/three-dogs.jpg",
      "status": "active",
      "access_mode": "public",
      "access_control": null,
      "etag": "bea5361cd1b0fe31c431426cf85a1fde",
      "created_by": null,
      "uploaded_by": null
    },
    {
      "asset_id": "fdcbbe6215ace8010921b7df235f8837",
      "public_id": "samples/people/jazz",
      "folder": "samples/people",
      "filename": "jazz",
      "display_name": null,
      "format": "jpg",
      "version": 1635454189,
      "resource_type": "image",
      "type": "upload",
      "created_at": "2021-10-28T20:49:49+00:00",
      "uploaded_at": "2021-10-28T20:49:49+00:00",
      "bytes": 695548,
      "backup_bytes": 0,
      "width": 3000,
      "height": 1993,
      "aspect_ratio": 1.50527,
      "pixels": 5979000,
      "url": "http://res.cloudinary.com/milliegrey/image/upload/v1635454189/samples/people/jazz.jpg",
      "secure_url": "https://res.cloudinary.com/milliegrey/image/upload/v1635454189/samples/people/jazz.jpg",
      "status": "active",
      "access_mode": "public",
      "access_control": null,
      "etag": "fc760976400724ae3e1fcbc56366e321",
      "created_by": null,
      "uploaded_by": null
    },
    {
      "asset_id": "a38cae1b40b76f826c3cf5e858b0f2ac",
      "public_id": "samples/people/boy-snow-hoodie",
      "folder": "samples/people",
      "filename": "boy-snow-hoodie",
      "display_name": null,
      "format": "jpg",
      "version": 1635454189,
      "resource_type": "image",
      "type": "upload",
      "created_at": "2021-10-28T20:49:49+00:00",
      "uploaded_at": "2021-10-28T20:49:49+00:00",
      "bytes": 581238,
      "backup_bytes": 0,
      "width": 1777,
      "height": 1332,
      "aspect_ratio": 1.33408,
      "pixels": 2366964,
      "url": "http://res.cloudinary.com/milliegrey/image/upload/v1635454189/samples/people/boy-snow-hoodie.jpg",
      "secure_url": "https://res.cloudinary.com/milliegrey/image/upload/v1635454189/samples/people/boy-snow-hoodie.jpg",
      "status": "active",
      "access_mode": "public",
      "access_control": null,
      "etag": "9f36975158ae4138b3fce4f6a84ec653",
      "created_by": null,
      "uploaded_by": null
    },
    {
      "asset_id": "ae0f270ff380bec1294bc314ce65951f",
      "public_id": "samples/bike",
      "folder": "samples",
      "filename": "bike",
      "display_name": null,
      "format": "jpg",
      "version": 1635454188,
      "resource_type": "image",
      "type": "upload",
      "created_at": "2021-10-28T20:49:48+00:00",
      "uploaded_at": "2021-10-28T20:49:48+00:00",
      "bytes": 475687,
      "backup_bytes": 0,
      "width": 2000,
      "height": 1333,
      "aspect_ratio": 1.50038,
      "pixels": 2666000,
      "url": "http://res.cloudinary.com/milliegrey/image/upload/v1635454188/samples/bike.jpg",
      "secure_url": "https://res.cloudinary.com/milliegrey/image/upload/v1635454188/samples/bike.jpg",
      "status": "active",
      "access_mode": "public",
      "access_control": null,
      "etag": "1321c993d60dbc94379007f1768809b8",
      "created_by": null,
      "uploaded_by": null
    },
    {
      "asset_id": "8487617ed92ba6ed43052dac2bb2ae1c",
      "public_id": "samples/ecommerce/shoes",
      "folder": "samples/ecommerce",
      "filename": "shoes",
      "display_name": null,
      "format": "png",
      "version": 1635454188,
      "resource_type": "image",
      "type": "upload",
      "created_at": "2021-10-28T20:49:48+00:00",
      "uploaded_at": "2021-10-28T20:49:48+00:00",
      "bytes": 393265,
      "backup_bytes": 0,
      "width": 587,
      "height": 507,
      "aspect_ratio": 1.15779,
      "pixels": 297609,
      "url": "http://res.cloudinary.com/milliegrey/image/upload/v1635454188/samples/ecommerce/shoes.png",
      "secure_url": "https://res.cloudinary.com/milliegrey/image/upload/v1635454188/samples/ecommerce/shoes.png",
      "status": "active",
      "access_mode": "public",
      "access_control": null,
      "etag": "87235c9653a64f3568650b10e3f39a3e",
      "created_by": null,
      "uploaded_by": null
    },
    {
      "asset_id": "4b6e4ad9bf1954e21a8df1c1e2d83f5e",
      "public_id": "samples/landscapes/girl-urban-view",
      "folder": "samples/landscapes",
      "filename": "girl-urban-view",
      "display_name": null,
      "format": "jpg",
      "version": 1635454187,
      "resource_type": "image",
      "type": "upload",
      "created_at": "2021-10-28T20:49:47+00:00",
      "uploaded_at": "2021-10-28T20:49:47+00:00",
      "bytes": 372778,
      "backup_bytes": 0,
      "width": 2048,
      "height": 1252,
      "aspect_ratio": 1.63578,
      "pixels": 2564096,
      "url": "http://res.cloudinary.com/milliegrey/image/upload/v1635454187/samples/landscapes/girl-urban-view.jpg",
      "secure_url": "https://res.cloudinary.com/milliegrey/image/upload/v1635454187/samples/landscapes/girl-urban-view.jpg",
      "status": "active",
      "access_mode": "public",
      "access_control": null,
      "etag": "5067b607472eb855fba7f56254b198f2",
      "created_by": null,
      "uploaded_by": null
    },
    {
      "asset_id": "2fcafb53f5c416918ef528612b5adf92",
      "public_id": "samples/people/smiling-man",
      "folder": "samples/people",
      "filename": "smiling-man",
      "display_name": null,
      "format": "jpg",
      "version": 1635454187,
      "resource_type": "image",
      "type": "upload",
      "created_at": "2021-10-28T20:49:47+00:00",
      "uploaded_at": "2021-10-28T20:49:47+00:00",
      "bytes": 338794,
      "backup_bytes": 0,
      "width": 849,
      "height": 565,
      "aspect_ratio": 1.50265,
      "pixels": 479685,
      "url": "http://res.cloudinary.com/milliegrey/image/upload/v1635454187/samples/people/smiling-man.jpg",
      "secure_url": "https://res.cloudinary.com/milliegrey/image/upload/v1635454187/samples/people/smiling-man.jpg",
      "status": "active",
      "access_mode": "public",
      "access_control": null,
      "etag": "a70d67e1107e15e2a3d51e1205bd7b78",
      "created_by": null,
      "uploaded_by": null
    },
    {
      "asset_id": "8fe261f0546a6250833a340741febca9",
      "public_id": "samples/sheep",
      "folder": "samples",
      "filename": "sheep",
      "display_name": null,
      "format": "jpg",
      "version": 1635454187,
      "resource_type": "image",
      "type": "upload",
      "created_at": "2021-10-28T20:49:47+00:00",
      "uploaded_at": "2021-10-28T20:49:47+00:00",
      "bytes": 269304,
      "backup_bytes": 0,
      "width": 1600,
      "height": 1067,
      "aspect_ratio": 1.49953,
      "pixels": 1707200,
      "url": "http://res.cloudinary.com/milliegrey/image/upload/v1635454187/samples/sheep.jpg",
      "secure_url": "https://res.cloudinary.com/milliegrey/image/upload/v1635454187/samples/sheep.jpg",
      "status": "active",
      "access_mode": "public",
      "access_control": null,
      "etag": "d6cbc36fafac8ee40f8d686be1b0f54c",
      "created_by": null,
      "uploaded_by": null
    },
    {
      "asset_id": "c1ee0f5a7c93d3a9d6efff9f6a4e5a57",
      "public_id": "samples/food/pot-mussels",
      "folder": "samples/food",
      "filename": "pot-mussels",
      "display_name": null,
      "format": "jpg",
      "version": 1635454186,
      "resource_type": "image",
      "type": "upload",
      "created_at": "2021-10-28T20:49:46+00:00",
      "uploaded_at": "2021-10-28T20:49:46+00:00",
      "bytes": 191852,
      "backup_bytes": 0,
      "width": 1220,
      "height": 818,
      "aspect_ratio": 1.49144,
      "pixels": 997960,
      "url": "http://res.cloudinary.com/milliegrey/image/upload/v1635454186/samples/food/pot-mussels.jpg",
      "secure_url": "https://res.cloudinary.com/milliegrey/image/upload/v1635454186/samples/food/pot-mussels.jpg",
      "status": "active",
      "access_mode": "public",
      "access_control": null,
      "etag": "80b79eb6de452646d1d9cd19f8091682",
      "created_by": null,
      "uploaded_by": null
    },
    {
      "asset_id": "94a4e4c37f29aae4a2722e4e46e4e6c2",
      "public_id": "samples/food/fish-vegetables",
      "folder": "samples/food",
      "filename": "fish-vegetables",
      "display_name": null,
      "format": "jpg",
      "version": 1635454186,
      "resource_type": "image",
      "type": "upload",
      "created_at": "2021-10-28T20:49:46+00:00",
      "uploaded_at": "2021-10-28T20:49:46+00:00",
      "bytes": 169013,
      "backup_bytes": 0,
      "width": 1220,
      "height": 813,
      "aspect_ratio": 1.50062,
      "pixels": 991860,
      "url": "http://res.cloudinary.com/milliegrey/image/upload/v1635454186/samples/food/fish-vegetables.jpg",
      "secure_url": "https://res.cloudinary.com/milliegrey/image/upload/v1635454186/samples/food/fish-vegetables.jpg",
      "status": "active",
      "access_mode": "public",
      "access_control": null,
      "etag": "3e883f65c756d49a6aa2dae4a40beda0",
      "created_by": null,
      "uploaded_by": null
    },
    {
      "asset_id": "d460c6e39ffd100f60dc16f57aaf4a27",
      "public_id": "samples/animals/reindeer",
      "folder": "samples/animals",
      "filename": "reindeer",
      "display_name": null,
      "format": "jpg",
      "version": 1635454185,
      "resource_type": "image",
      "type": "upload",
      "created_at": "2021-10-28T20:49:45+00:00",
      "uploaded_at": "2021-10-28T20:49:45+00:00",
      "bytes": 161150,
      "backup_bytes": 0,
      "width": 1220,
      "height": 813,
      "aspect_ratio": 1.50062,
      "pixels": 991860,
      "url": "http://res.cloudinary.com/milliegrey/image/upload/v1635454185/samples/animals/reindeer.jpg",
      "secure_url": "https://res.cloudinary.com/milliegrey/image/upload/v1635454185/samples/animals/reindeer.jpg",
      "status": "active",
      "access_mode": "public",
      "access_control": null,
      "etag": "9497692c276d169eb9a5c6fd147c2d7b",
      "created_by": null,
      "uploaded_by": null
    },
    {
      "asset_id": "9a7261b428062e7516e237ed208410bc",
      "public_id": "samples/people/kitchen-bar",
      "folder": "samples/people",
      "filename": "kitchen-bar",
      "display_name": null,
      "format": "jpg",
      "version": 1635454185,
      "resource_type": "image",
      "type": "upload",
      "created_at": "2021-10-28T20:49:45+00:00",
      "uploaded_at": "2021-10-28T20:49:45+00:00",
      "bytes": 154151,
      "backup_bytes": 0,
      "width": 1220,
      "height": 813,
      "aspect_ratio": 1.50062,
      "pixels": 991860,
      "url": "http://res.cloudinary.com/milliegrey/image/upload/v1635454185/samples/people/kitchen-bar.jpg",
      "secure_url": "https://res.cloudinary.com/milliegrey/image/upload/v1635454185/samples/people/kitchen-bar.jpg",
      "status": "active",
      "access_mode": "public",
      "access_control": null,
      "etag": "01036ab24b43ff3651904327947a10aa",
      "created_by": null,
      "uploaded_by": null
    },
    {
      "asset_id": "7b632e86f7942b5cf2621dec7f4be53e",
      "public_id": "samples/food/dessert",
      "folder": "samples/food",
      "filename": "dessert",
      "display_name": null,
      "format": "jpg",
      "version": 1635454185,
      "resource_type": "image",
      "type": "upload",
      "created_at": "2021-10-28T20:49:45+00:00",
      "uploaded_at": "2021-10-28T20:49:45+00:00",
      "bytes": 125888,
      "backup_bytes": 0,
      "width": 1220,
      "height": 813,
      "aspect_ratio": 1.50062,
      "pixels": 991860,
      "url": "http://res.cloudinary.com/milliegrey/image/upload/v1635454185/samples/food/dessert.jpg",
      "secure_url": "https://res.cloudinary.com/milliegrey/image/upload/v1635454185/samples/food/dessert.jpg",
      "status": "active",
      "access_mode": "public",
      "access_control": null,
      "etag": "2a341d493016230b4b243db5a8b14423",
      "created_by": null,
      "uploaded_by": null
    },
    {
      "asset_id": "af6353325cd46c6365da27df04f28316",
      "public_id": "samples/animals/cat",
      "folder": "samples/animals",
      "filename": "cat",
      "display_name": null,
      "format": "jpg",
      "version": 1635454184,
      "resource_type": "image",
      "type": "upload",
      "created_at": "2021-10-28T20:49:44+00:00",
      "uploaded_at": "2021-10-28T20:49:44+00:00",
      "bytes": 92690,
      "backup_bytes": 0,
      "width": 768,
      "height": 1024,
      "aspect_ratio": 0.75,
      "pixels": 786432,
      "url": "http://res.cloudinary.com/milliegrey/image/upload/v1635454184/samples/animals/cat.jpg",
      "secure_url": "https://res.cloudinary.com/milliegrey/image/upload/v1635454184/samples/animals/cat.jpg",
      "status": "active",
      "access_mode": "public",
      "access_control": null,
      "etag": "0a9c1edee9462e02de5b3d3096c6eb87",
      "created_by": null,
      "uploaded_by": null
    },
    {
      "asset_id": "b10df87fe316d86d728079fa07f7dfbc",
      "public_id": "samples/ecommerce/analog-classic",
      "folder": "samples/ecommerce",
      "filename": "analog-classic",
      "display_name": null,
      "format": "jpg",
      "version": 1635454184,
      "resource_type": "image",
      "type": "upload",
      "created_at": "2021-10-28T20:49:44+00:00",
      "uploaded_at": "2021-10-28T20:49:44+00:00",
      "bytes": 72558,
      "backup_bytes": 0,
      "width": 1280,
      "height": 853,
      "aspect_ratio": 1.50059,
      "pixels": 1091840,
      "url": "http://res.cloudinary.com/milliegrey/image/upload/v1635454184/samples/ecommerce/analog-classic.jpg",
      "secure_url": "https://res.cloudinary.com/milliegrey/image/upload/v1635454184/samples/ecommerce/analog-classic.jpg",
      "status": "active",
      "access_mode": "public",
      "access_control": null,
      "etag": "cf8f1bed5f95fd0ff6738a1ea1e72b56",
      "created_by": null,
      "uploaded_by": null
    },
    {
      "asset_id": "3c6e4f0b5654329a3126fb8b8bfec0cf",
      "public_id": "samples/cloudinary-logo-vector",
      "folder": "samples",
      "filename": "cloudinary-logo-vector",
      "display_name": null,
      "format": "svg",
      "version": 1635454182,
      "resource_type": "image",
      "type": "upload",
      "created_at": "2021-10-28T20:49:42+00:00",
      "uploaded_at": "2021-10-28T20:49:42+00:00",
      "bytes": 21816,
      "backup_bytes": 0,
      "width": 155,
      "height": 155,
      "aspect_ratio": 1.0,
      "pixels": 24025,
      "url": "http://res.cloudinary.com/milliegrey/image/upload/v1635454182/samples/cloudinary-logo-vector.svg",
      "secure_url": "https://res.cloudinary.com/milliegrey/image/upload/v1635454182/samples/cloudinary-logo-vector.svg",
      "status": "active",
      "access_mode": "public",
      "access_control": null,
      "etag": "27868c91740ac50f5616cbe45ff008db",
      "created_by": null,
      "uploaded_by": null
    },
    {
      "asset_id": "107f306f72dcac0074ad2f18f1529690",
      "public_id": "samples/cloudinary-icon",
      "folder": "samples",
      "filename": "cloudinary-icon",
      "display_name": null,
      "format": "png",
      "version": 1635454182,
      "resource_type": "image",
      "type": "upload",
      "created_at": "2021-10-28T20:49:42+00:00",
      "uploaded_at": "2021-10-28T20:49:42+00:00",
      "bytes": 10099,
      "backup_bytes": 0,
      "width": 480,
      "height": 350,
      "aspect_ratio": 1.37143,
      "pixels": 168000,
      "url": "http://res.cloudinary.com/milliegrey/image/upload/v1635454182/samples/cloudinary-icon.png",
      "secure_url": "https://res.cloudinary.com/milliegrey/image/upload/v1635454182/samples/cloudinary-icon.png",
      "status": "active",
      "access_mode": "public",
      "access_control": null,
      "etag": "f08f89e33e45fccc8fc8bc89bd48e329",
      "created_by": null,
      "uploaded_by": null
    },
    {
      "asset_id": "56eef130563bc9bf8cb95e9dd1de3749",
      "public_id": "sample",
      "folder": "",
      "filename": "sample",
      "display_name": null,
      "format": "jpg",
      "version": 1635454181,
      "resource_type": "image",
      "type": "upload",
      "created_at": "2021-10-28T20:49:41+00:00",
      "uploaded_at": "2021-10-28T20:49:41+00:00",
      "bytes": 120253,
      "backup_bytes": 0,
      "width": 864,
      "height": 576,
      "aspect_ratio": 1.5,
      "pixels": 497664,
      "url": "http://res.cloudinary.com/milliegrey/image/upload/v1635454181/sample.jpg",
      "secure_url": "https://res.cloudinary.com/milliegrey/image/upload/v1635454181/sample.jpg",
      "status": "active",
      "access_mode": "public",
      "access_control": null,
      "etag": "83340520d28b704ca4f4b019effb33dc",
      "created_by": null,
      "uploaded_by": null
    }
  ]
}
